<?xml version="1.0" encoding="UTF-8" ?>
<!DOCTYPE mapper PUBLIC "-//mybatis.org//DTD Mapper 3.0//EN"
    "http://mybatis.org/dtd/mybatis-3-mapper.dtd">

<mapper namespace="com.nexacro.uiadapter.mapper.FileMapper">

    <insert id="insert" parameterType="com.nexacro.uiadapter.domain.FileMeta">
        INSERT INTO FILE_META (FILE_ID, ORIGINAL_NAME, STORED_PATH, CONTENT_TYPE, SIZE_BYTES, UPLOADED_BY)
        VALUES (
            #{fileId},
            #{originalName},
            #{storedPath},
            #{contentType},
            #{sizeBytes},
            #{uploadedBy}
        )
    </insert>

    <select id="selectById" parameterType="string"
            resultType="com.nexacro.uiadapter.domain.FileMeta">
        SELECT FILE_ID, ORIGINAL_NAME, STORED_PATH, CONTENT_TYPE, SIZE_BYTES,
               UPLOADED_BY, UPLOADED_AT, DELETED
        FROM FILE_META
        WHERE FILE_ID = #{fileId}
          AND DELETED = FALSE
    </select>

    <select id="selectList" resultType="com.nexacro.uiadapter.domain.FileMeta">
        SELECT FILE_ID, ORIGINAL_NAME, STORED_PATH, CONTENT_TYPE, SIZE_BYTES,
               UPLOADED_BY, UPLOADED_AT, DELETED
        FROM FILE_META
        WHERE DELETED = FALSE
        ORDER BY UPLOADED_AT DESC
    </select>

    <select id="selectByIds" resultType="com.nexacro.uiadapter.domain.FileMeta">
        SELECT FILE_ID, ORIGINAL_NAME, STORED_PATH, CONTENT_TYPE, SIZE_BYTES,
               UPLOADED_BY, UPLOADED_AT, DELETED
        FROM FILE_META
        WHERE DELETED = FALSE
          AND FILE_ID IN
        <foreach item="id" collection="ids" open="(" separator="," close=")">
            #{id}
        </foreach>
    </select>

</mapper>
