<?xml version="1.0" encoding="UTF-8" ?>
<!DOCTYPE mapper PUBLIC "-//mybatis.org//DTD Mapper 3.0//EN"
    "http://mybatis.org/dtd/mybatis-3-mapper.dtd">

<mapper namespace="com.nexacro.uiadapter.mapper.BoardMapper">

    <select id="selectList" parameterType="com.nexacro.uiadapter.domain.Board"
            resultType="com.nexacro.uiadapter.domain.Board">
        SELECT POST_ID, TITLE, CONTENTS, REG_ID, REG_DATE, COMMUNITY_ID, HIDDEN_INFO, HIT_COUNT, IS_NOTICE
        FROM TB_BOARD
        <where>
            <if test="regId != null and regId != ''">
                AND REG_ID = #{regId}
            </if>
            <if test="title != null and title != ''">
                AND TITLE LIKE '%' || #{title} || '%'
            </if>
            <if test="communityId != null and communityId != ''">
                AND COMMUNITY_ID = #{communityId}
            </if>
        </where>
        ORDER BY POST_ID DESC
    </select>

    <select id="selectById" parameterType="int"
            resultType="com.nexacro.uiadapter.domain.Board">
        SELECT POST_ID, TITLE, CONTENTS, REG_ID, REG_DATE, COMMUNITY_ID, HIDDEN_INFO, HIT_COUNT, IS_NOTICE
        FROM TB_BOARD
        WHERE POST_ID = #{postId}
    </select>

    <insert id="insert" parameterType="com.nexacro.uiadapter.domain.Board"
            useGeneratedKeys="true" keyProperty="postId" keyColumn="POST_ID">
        INSERT INTO TB_BOARD (TITLE, CONTENTS, REG_ID, REG_DATE, COMMUNITY_ID, HIDDEN_INFO, HIT_COUNT, IS_NOTICE)
        VALUES (
            #{title},
            #{contents},
            #{regId},
            <choose>
                <when test="regDate != null">#{regDate}</when>
                <otherwise>CURRENT_DATE</otherwise>
            </choose>,
            #{communityId},
            #{hiddenInfo},
            <choose>
                <when test="hitCount != null">#{hitCount}</when>
                <otherwise>0</otherwise>
            </choose>,
            <choose>
                <when test="isNotice != null">#{isNotice}</when>
                <otherwise>FALSE</otherwise>
            </choose>
        )
    </insert>

    <update id="update" parameterType="com.nexacro.uiadapter.domain.Board">
        UPDATE TB_BOARD
        SET TITLE        = #{title},
            CONTENTS     = #{contents},
            COMMUNITY_ID = #{communityId},
            HIDDEN_INFO  = #{hiddenInfo},
            HIT_COUNT    = #{hitCount},
            IS_NOTICE    = #{isNotice}
        WHERE POST_ID = #{postId}
    </update>

    <delete id="softDelete" parameterType="int">
        DELETE FROM TB_BOARD
        WHERE POST_ID = #{postId}
    </delete>

</mapper>
